corus-stubs/METADATA.toml
corus-stubs/__init__.pyi
corus-stubs/io.pyi
corus-stubs/path.pyi
corus-stubs/py.typed
corus-stubs/readme.pyi
corus-stubs/record.pyi
corus-stubs/zip.pyi
corus-stubs/sources/__init__.pyi
corus-stubs/sources/bsnlp.pyi
corus-stubs/sources/buriy.pyi
corus-stubs/sources/corpora.pyi
corus-stubs/sources/factru.pyi
corus-stubs/sources/gareev.pyi
corus-stubs/sources/gramru.pyi
corus-stubs/sources/lenta.pyi
corus-stubs/sources/librusec.pyi
corus-stubs/sources/meta.pyi
corus-stubs/sources/mokoron.pyi
corus-stubs/sources/morphoru.pyi
corus-stubs/sources/ne5.pyi
corus-stubs/sources/ods.pyi
corus-stubs/sources/omnia.pyi
corus-stubs/sources/persons.pyi
corus-stubs/sources/ria.pyi
corus-stubs/sources/rudrec.pyi
corus-stubs/sources/russe.pyi
corus-stubs/sources/simlex.pyi
corus-stubs/sources/toloka.pyi
corus-stubs/sources/ud.pyi
corus-stubs/sources/wiki.pyi
corus-stubs/sources/wikiner.pyi
corus-stubs/sources/taiga/__init__.pyi
corus-stubs/sources/taiga/arzamas.pyi
corus-stubs/sources/taiga/common.pyi
corus-stubs/sources/taiga/fontanka.pyi
corus-stubs/sources/taiga/interfax.pyi
corus-stubs/sources/taiga/kp.pyi
corus-stubs/sources/taiga/lenta.pyi
corus-stubs/sources/taiga/magazines.pyi
corus-stubs/sources/taiga/nplus1.pyi
corus-stubs/sources/taiga/proza.pyi
corus-stubs/sources/taiga/social.pyi
corus-stubs/sources/taiga/subtitles.pyi
corus-stubs/third/WikiExtractor.pyi
corus-stubs/third/__init__.pyi
types_corus-0.10.0.20250516.dist-info/licenses/LICENSE
types_corus-0.10.0.20250516.dist-info/METADATA
types_corus-0.10.0.20250516.dist-info/WHEEL
types_corus-0.10.0.20250516.dist-info/top_level.txt
types_corus-0.10.0.20250516.dist-info/RECORD
